{
    "en": [
        {
            "linkdashboard": "Link Dashboard",
            "add": "Add",
            "selectDate": "Select Date",
            "search": "Search",
            "count": "Count",
            "date": "Date",
            "type": "Type",
            "email": "Email",
            "status": "Status",
            "previous": "Previous",
            "next": "Next",
            "generateLink": "Generate Link",
            "selectType": "Select Type",
            "hospital": "Hospital",
            "inClinic": "InClinc",
            "independentDoctor": "Independent Doctor",
            "independentNurse": "Independet Nurse",
            "independentPhysiotherapist": "Independent Physiotherapist",
            "independentMidwife": "Independent Midwife",
            "pharmacy": "Pharmacy",
            "diagnosticCenter": "Diagnostic Center",
            "username": "Username",
            "password": "Password",
            "description": "Description",
            "remarks": "Remarks",
            "save": "Save",
            "back": "Back",
            "registeredDashboard": "Registered Dashboard",
            "name": "Name",
            "phoneNumber": "Phone Number",
            "address": "Address",
            "actions": "Actions",
            "clinic": "Clinic",
            "nurse": "Nurse",
            "male": "Male",
            "female": "Female",
            "waitingForApproval": "Waiting For Approval",
            "approve": "Approve",
            "reject": "Reject",
            "approvedusersDashboard": "Approved Users Dashboard",
            "rejectedUserDashboard": "Rejected User Dashboard",
            "phonevalidtest": "Please use a minimum of 8 characters. The password must be a combination of uppercase letters, numbers and special characters.",
            "saveandcontinue": "Save and send",
            "gender": "gender",
            "doctorName": "Doctor name",
            "experience": "Experience",
            "doctorType": "Doctor Type",
            "speaklanguge": "SPEAK LANGUAGES",
            "registrationNumber": "Registration number",
            "registrationCouncil": "Registration Council",
            "slotDuration": "Slot Duration",
            "college": "College",
            "otherExperiences": "Other Experiences",
            "profilePhoto": "Profile photo",
            "medicalRegistrationProof": "Medical registration Proof",
            "hospitalClinicName": "Clinic Name",
            "hospitalPhoneNo": "Hospital PhoneNo",
            "contactPersonName": "Contact Person Name",
            "contactPersonPhoneNumber": "Contact Person PhoneNumber",
            "website": "Web site",
            "yearEstablished": "Year Established",
            "identityProof": "identityProof",
            "view": "view",
            "details": "Details",
            "resume": "Resume",
            "rejectText": "You Want to Reject This!",
            "rejectButton":"Yes, Reject it!",
            "areYouSure":"Are you sure?"
        }
    ],
    "fr": [
        {
            "linkdashboard": "LIEN ENREGISTREMENT",
            "add": "Ajouter des candidats",
            "selectDate": "Sélecteur de date",
            "search": "Rechercher",
            "count": " Nombre",
            "date": "Date",
            "type": "Type",
            "email": "Email",
            "status": "Statut",
            "previous": "Précédent",
            "next": "Suviant",
            "generateLink": "LANCER LE LIEN D'INSCRIPTION",
            "selectType": "Sélectionner un prestataire",
            "hospital": "Hôpitalux",
            "inClinic": "Cliniques",
            "independentDoctor": "Médecin independents",
            "independentNurse": "Infirmière indépendantes",
            "independentPhysiotherapist": "Soignant indépendant",
            "independentMidwife": "Sage-femme indépendantes",
            "pharmacy": "Pharmacies",
            "diagnosticCenter": "Centres analyses et imageries",
            "username": "Nom d'utilisateur",
            "password": "Votre mot de passe",
            "description": "Lien d'inscription",
            "remarks": "Remarques",
            "save": "Sauvegarder",
            "back": "Retour",
            "registeredDashboard": "CANDIDATS INSCRITS",
            "name": "Nom",
            "phoneNumber": "No de tél",
            "address": "Adresse",
            "actions": "Actions",
            "clinic": "Cliniques",
            "nurse": "Infirmière",
            "male": "Masculin",
            "female": "Féminin",
            "waitingForApproval": "En Attente d'approbation",
            "approve": "Approuver",
            "reject": "Rejeter",
            "approvedusersDashboard": "INSCRIPTION APPROUVÉE",
            "rejectedUserDashboard": "INSCRIPTION REJETÉE",
            "phonevalidtest": "Veuillez utiliser un minimum de 8 caractères. Le mot de passe doit être une combinaison de lettres majuscules, de chiffres et de caractères spéciaux.",
            "saveandcontinue": "Enregistrerenvoyer",
            "gender": "gender",
            "doctorName": "Nom Du Docteur ",
            "experience": "Années de pratique",
            "doctorType": "Type De Docteur",
            "speaklanguge": "Langue(s) parlée(s)",
            "registrationNumber": "Numéro d’inscription",
            "registrationCouncil": "Délivrée Par",
            "slotDuration": "Durée de la consultation",
            "college": "Universite ",
            "otherExperiences": "Other ExperiencesAutres Expériences ",
            "profilePhoto": "Photo de profil :",
            "medicalRegistrationProof": "Copie carte professionnelle",
            "hospitalClinicName": "Clinic Name",
            "hospitalPhoneNo": "Hospital PhoneNo",
            "contactPersonName": "Contact Person Name",
            "contactPersonPhoneNumber": "Contact Person PhoneNumber",
            "website": "Web site",
            "yearEstablished": "Year Established",
            "identityProof": "identityProof",
            "view": "view",
            "details": "Dossier",
            "resume": "Resume",
            "rejectText": "Vous voulez rejeter ça !",
            "rejectButton":"Oui, rejetez-le!",
            "areYouSure":"Es-tu sûr?"
        }
    ]
}